{
  "type": "create:crushing",
  "ingredients": [
    {
      "fabric:type": "create:simple_datagen",
      "ingredients": [
        {
          "item": "elementaryores:ore_diamond_end"
        }
      ]
    }
  ],
  "porting_lib:conditions": [
    {
      "type": "neoforge:mod_loaded",
      "modid": "elementaryores"
    }
  ],
  "processing_time": 350,
  "results": [
    {
      "id": "minecraft:diamond"
    },
    {
      "chance": 0.25,
      "id": "minecraft:diamond"
    },
    {
      "chance": 0.75,
      "id": "create:experience_nugget"
    },
    {
      "chance": 0.12,
      "id": "minecraft:end_stone"
    }
  ]
}